{
  "classname": null,
  "name": null,
  "animation": {
    "classname": null,
    "name": "AnimationManager",
    "actionlist": []
  },
  "dataScale": 1,
  "designHeight": 640,
  "designWidth": 960,
  "textures": [
    "anniversary0.plist"
  ],
  "texturesPng": [
    "anniversary0.png"
  ],
  "version": "1.6.0.0",
  "widgetTree": {
    "classname": "Panel",
    "name": null,
    "children": [
      {
        "classname": "ImageView",
        "name": null,
        "children": [],
        "options": {
          "__type": "ImageViewSurrogate:#EditorCommon.JsonModel.Component.GUI",
          "classname": "ImageView",
          "name": "Image_2",
          "ZOrder": 0,
          "actiontag": 41270904,
          "anchorPointX": 0.5,
          "anchorPointY": 0.5,
          "classType": "CocoStudio.EngineAdapterWrap.CSImageView",
          "colorB": 255,
          "colorG": 255,
          "colorR": 255,
          "customProperty": "",
          "flipX": false,
          "flipY": false,
          "height": 546,
          "ignoreSize": true,
          "layoutParameter": null,
          "opacity": 255,
          "positionPercentX": 0.5,
          "positionPercentY": 0.5,
          "positionType": 0,
          "rotation": 0,
          "scaleX": 1,
          "scaleY": 1,
          "sizePercentX": 0.875,
          "sizePercentY": 0.853125,
          "sizeType": 0,
          "tag": 105,
          "touchAble": false,
          "useMergedTexture": false,
          "visible": true,
          "width": 840,
          "x": 480,
          "y": 320,
          "capInsetsHeight": 1,
          "capInsetsWidth": 1,
          "capInsetsX": 0,
          "capInsetsY": 0,
          "fileName": null,
          "fileNameData": {
            "path": "anniversary_bg.png",
            "plistFile": "",
            "resourceType": 0
          },
          "scale9Enable": false,
          "scale9Height": 546,
          "scale9Width": 840
        }
      },
      {
        "classname": "ImageView",
        "name": null,
        "children": [],
        "options": {
          "__type": "ImageViewSurrogate:#EditorCommon.JsonModel.Component.GUI",
          "classname": "ImageView",
          "name": "Image_4",
          "ZOrder": 0,
          "actiontag": 56272369,
          "anchorPointX": 0.5,
          "anchorPointY": 0.5,
          "classType": "CocoStudio.EngineAdapterWrap.CSImageView",
          "colorB": 255,
          "colorG": 255,
          "colorR": 255,
          "customProperty": "",
          "flipX": false,
          "flipY": false,
          "height": 192,
          "ignoreSize": true,
          "layoutParameter": null,
          "opacity": 255,
          "positionPercentX": 0.213541672,
          "positionPercentY": 0.3375,
          "positionType": 0,
          "rotation": 0,
          "scaleX": 1,
          "scaleY": 1,
          "sizePercentX": 0.141666666,
          "sizePercentY": 0.3,
          "sizeType": 0,
          "tag": 107,
          "touchAble": false,
          "useMergedTexture": false,
          "visible": true,
          "width": 136,
          "x": 205,
          "y": 216,
          "capInsetsHeight": 1,
          "capInsetsWidth": 1,
          "capInsetsX": 0,
          "capInsetsY": 0,
          "fileName": null,
          "fileNameData": {
            "path": "anniversary_red_close.png",
            "plistFile": "",
            "resourceType": 0
          },
          "scale9Enable": false,
          "scale9Height": 192,
          "scale9Width": 136
        }
      },
      {
        "classname": "ImageView",
        "name": null,
        "children": [],
        "options": {
          "__type": "ImageViewSurrogate:#EditorCommon.JsonModel.Component.GUI",
          "classname": "ImageView",
          "name": "Image_5",
          "ZOrder": 0,
          "actiontag": 66055606,
          "anchorPointX": 0.5,
          "anchorPointY": 0.5,
          "classType": "CocoStudio.EngineAdapterWrap.CSImageView",
          "colorB": 255,
          "colorG": 255,
          "colorR": 255,
          "customProperty": "",
          "flipX": false,
          "flipY": false,
          "height": 147,
          "ignoreSize": true,
          "layoutParameter": null,
          "opacity": 255,
          "positionPercentX": 0.410416663,
          "positionPercentY": 0.2859375,
          "positionType": 0,
          "rotation": 0,
          "scaleX": 1,
          "scaleY": 1,
          "sizePercentX": 0.130208328,
          "sizePercentY": 0.2296875,
          "sizeType": 0,
          "tag": 108,
          "touchAble": false,
          "useMergedTexture": false,
          "visible": true,
          "width": 125,
          "x": 394,
          "y": 183,
          "capInsetsHeight": 1,
          "capInsetsWidth": 1,
          "capInsetsX": 0,
          "capInsetsY": 0,
          "fileName": null,
          "fileNameData": {
            "path": "anniversary_medal.png",
            "plistFile": "",
            "resourceType": 0
          },
          "scale9Enable": false,
          "scale9Height": 147,
          "scale9Width": 125
        }
      },
      {
        "classname": "ImageView",
        "name": null,
        "children": [],
        "options": {
          "__type": "ImageViewSurrogate:#EditorCommon.JsonModel.Component.GUI",
          "classname": "ImageView",
          "name": "Image_6",
          "ZOrder": 0,
          "actiontag": 50149464,
          "anchorPointX": 0.5,
          "anchorPointY": 0.5,
          "classType": "CocoStudio.EngineAdapterWrap.CSImageView",
          "colorB": 255,
          "colorG": 255,
          "colorR": 255,
          "customProperty": "",
          "flipX": false,
          "flipY": false,
          "height": 147,
          "ignoreSize": true,
          "layoutParameter": null,
          "opacity": 255,
          "positionPercentX": 0.60625,
          "positionPercentY": 0.290625,
          "positionType": 0,
          "rotation": 0,
          "scaleX": 1,
          "scaleY": 1,
          "sizePercentX": 0.130208328,
          "sizePercentY": 0.2296875,
          "sizeType": 0,
          "tag": 109,
          "touchAble": false,
          "useMergedTexture": false,
          "visible": true,
          "width": 125,
          "x": 582,
          "y": 186,
          "capInsetsHeight": 1,
          "capInsetsWidth": 1,
          "capInsetsX": 0,
          "capInsetsY": 0,
          "fileName": null,
          "fileNameData": {
            "path": "anniversary_exp.png",
            "plistFile": "",
            "resourceType": 0
          },
          "scale9Enable": false,
          "scale9Height": 147,
          "scale9Width": 125
        }
      },
      {
        "classname": "ImageView",
        "name": null,
        "children": [],
        "options": {
          "__type": "ImageViewSurrogate:#EditorCommon.JsonModel.Component.GUI",
          "classname": "ImageView",
          "name": "Image_7",
          "ZOrder": 0,
          "actiontag": 30577469,
          "anchorPointX": 0.5,
          "anchorPointY": 0.5,
          "classType": "CocoStudio.EngineAdapterWrap.CSImageView",
          "colorB": 255,
          "colorG": 255,
          "colorR": 255,
          "customProperty": "",
          "flipX": false,
          "flipY": false,
          "height": 147,
          "ignoreSize": true,
          "layoutParameter": null,
          "opacity": 255,
          "positionPercentX": 0.79375,
          "positionPercentY": 0.290625,
          "positionType": 0,
          "rotation": 0,
          "scaleX": 1,
          "scaleY": 1,
          "sizePercentX": 0.130208328,
          "sizePercentY": 0.2296875,
          "sizeType": 0,
          "tag": 110,
          "touchAble": false,
          "useMergedTexture": false,
          "visible": true,
          "width": 125,
          "x": 762,
          "y": 186,
          "capInsetsHeight": 1,
          "capInsetsWidth": 1,
          "capInsetsX": 0,
          "capInsetsY": 0,
          "fileName": null,
          "fileNameData": {
            "path": "anniversary_hddj.png",
            "plistFile": "",
            "resourceType": 0
          },
          "scale9Enable": false,
          "scale9Height": 147,
          "scale9Width": 125
        }
      },
      {
        "classname": "Button",
        "name": null,
        "children": [],
        "options": {
          "__type": "ButtonSurrogate:#EditorCommon.JsonModel.Component.GUI",
          "classname": "Button",
          "name": "Button_8",
          "ZOrder": 0,
          "actiontag": 42863119,
          "anchorPointX": 0.5,
          "anchorPointY": 0.5,
          "classType": "CocoStudio.EngineAdapterWrap.CSButton",
          "colorB": 255,
          "colorG": 255,
          "colorR": 255,
          "customProperty": "",
          "flipX": false,
          "flipY": false,
          "height": 44,
          "ignoreSize": true,
          "layoutParameter": null,
          "opacity": 255,
          "positionPercentX": 0.830208361,
          "positionPercentY": 0.6546875,
          "positionType": 0,
          "rotation": 0,
          "scaleX": 1,
          "scaleY": 1,
          "sizePercentX": 0.14791666,
          "sizePercentY": 0.06875,
          "sizeType": 0,
          "tag": 111,
          "touchAble": true,
          "useMergedTexture": false,
          "visible": true,
          "width": 142,
          "x": 797,
          "y": 419,
          "capInsetsHeight": 1,
          "capInsetsWidth": 1,
          "capInsetsX": 0,
          "capInsetsY": 0,
          "disabled": null,
          "disabledData": {
            "path": null,
            "plistFile": null,
            "resourceType": 0
          },
          "fontName": "微软雅黑",
          "fontSize": 22,
          "fontType": 0,
          "normal": null,
          "normalData": {
            "path": "anniversary_button.png",
            "plistFile": "",
            "resourceType": 0
          },
          "pressed": null,
          "pressedData": {
            "path": null,
            "plistFile": null,
            "resourceType": 0
          },
          "scale9Enable": false,
          "scale9Height": 44,
          "scale9Width": 142,
          "text": "邀请好友",
          "textColorB": 0,
          "textColorG": 104,
          "textColorR": 49
        }
      },
      {
        "classname": "Button",
        "name": null,
        "children": [],
        "options": {
          "__type": "ButtonSurrogate:#EditorCommon.JsonModel.Component.GUI",
          "classname": "Button",
          "name": "Button_9",
          "ZOrder": 0,
          "actiontag": 54685102,
          "anchorPointX": 0.5,
          "anchorPointY": 0.5,
          "classType": "CocoStudio.EngineAdapterWrap.CSButton",
          "colorB": 255,
          "colorG": 255,
          "colorR": 255,
          "customProperty": "",
          "flipX": false,
          "flipY": false,
          "height": 44,
          "ignoreSize": true,
          "layoutParameter": null,
          "opacity": 255,
          "positionPercentX": 0.213541672,
          "positionPercentY": 0.115625,
          "positionType": 0,
          "rotation": 0,
          "scaleX": 1,
          "scaleY": 1,
          "sizePercentX": 0.14791666,
          "sizePercentY": 0.06875,
          "sizeType": 0,
          "tag": 112,
          "touchAble": true,
          "useMergedTexture": false,
          "visible": true,
          "width": 142,
          "x": 205,
          "y": 74,
          "capInsetsHeight": 1,
          "capInsetsWidth": 1,
          "capInsetsX": 0,
          "capInsetsY": 0,
          "disabled": null,
          "disabledData": {
            "path": null,
            "plistFile": null,
            "resourceType": 0
          },
          "fontName": "微软雅黑",
          "fontSize": 28,
          "fontType": 0,
          "normal": null,
          "normalData": {
            "path": "anniversary_button.png",
            "plistFile": "",
            "resourceType": 0
          },
          "pressed": null,
          "pressedData": {
            "path": null,
            "plistFile": null,
            "resourceType": 0
          },
          "scale9Enable": false,
          "scale9Height": 44,
          "scale9Width": 142,
          "text": "分享给好友",
          "textColorB": 0,
          "textColorG": 104,
          "textColorR": 49
        }
      },
      {
        "classname": "Button",
        "name": null,
        "children": [],
        "options": {
          "__type": "ButtonSurrogate:#EditorCommon.JsonModel.Component.GUI",
          "classname": "Button",
          "name": "Button_10",
          "ZOrder": 0,
          "actiontag": 37868406,
          "anchorPointX": 0.5,
          "anchorPointY": 0.5,
          "classType": "CocoStudio.EngineAdapterWrap.CSButton",
          "colorB": 255,
          "colorG": 255,
          "colorR": 255,
          "customProperty": "",
          "flipX": false,
          "flipY": false,
          "height": 44,
          "ignoreSize": true,
          "layoutParameter": null,
          "opacity": 255,
          "positionPercentX": 0.410416663,
          "positionPercentY": 0.115625,
          "positionType": 0,
          "rotation": 0,
          "scaleX": 1,
          "scaleY": 1,
          "sizePercentX": 0.14791666,
          "sizePercentY": 0.06875,
          "sizeType": 0,
          "tag": 113,
          "touchAble": true,
          "useMergedTexture": false,
          "visible": true,
          "width": 142,
          "x": 394,
          "y": 74,
          "capInsetsHeight": 1,
          "capInsetsWidth": 1,
          "capInsetsX": 0,
          "capInsetsY": 0,
          "disabled": null,
          "disabledData": {
            "path": null,
            "plistFile": null,
            "resourceType": 0
          },
          "fontName": "微软雅黑",
          "fontSize": 28,
          "fontType": 0,
          "normal": null,
          "normalData": {
            "path": "anniversary_button.png",
            "plistFile": "",
            "resourceType": 0
          },
          "pressed": null,
          "pressedData": {
            "path": null,
            "plistFile": null,
            "resourceType": 0
          },
          "scale9Enable": false,
          "scale9Height": 44,
          "scale9Width": 142,
          "text": "领取",
          "textColorB": 0,
          "textColorG": 104,
          "textColorR": 49
        }
      },
      {
        "classname": "Button",
        "name": null,
        "children": [],
        "options": {
          "__type": "ButtonSurrogate:#EditorCommon.JsonModel.Component.GUI",
          "classname": "Button",
          "name": "Button_11",
          "ZOrder": 0,
          "actiontag": 9296575,
          "anchorPointX": 0.5,
          "anchorPointY": 0.5,
          "classType": "CocoStudio.EngineAdapterWrap.CSButton",
          "colorB": 255,
          "colorG": 255,
          "colorR": 255,
          "customProperty": "",
          "flipX": false,
          "flipY": false,
          "height": 44,
          "ignoreSize": true,
          "layoutParameter": null,
          "opacity": 255,
          "positionPercentX": 0.60625,
          "positionPercentY": 0.115625,
          "positionType": 0,
          "rotation": 0,
          "scaleX": 1,
          "scaleY": 1,
          "sizePercentX": 0.14791666,
          "sizePercentY": 0.06875,
          "sizeType": 0,
          "tag": 114,
          "touchAble": true,
          "useMergedTexture": false,
          "visible": true,
          "width": 142,
          "x": 582,
          "y": 74,
          "capInsetsHeight": 1,
          "capInsetsWidth": 1,
          "capInsetsX": 0,
          "capInsetsY": 0,
          "disabled": null,
          "disabledData": {
            "path": null,
            "plistFile": null,
            "resourceType": 0
          },
          "fontName": "微软雅黑",
          "fontSize": 28,
          "fontType": 0,
          "normal": null,
          "normalData": {
            "path": "anniversary_button.png",
            "plistFile": "",
            "resourceType": 0
          },
          "pressed": null,
          "pressedData": {
            "path": null,
            "plistFile": null,
            "resourceType": 0
          },
          "scale9Enable": false,
          "scale9Height": 44,
          "scale9Width": 142,
          "text": "兑换",
          "textColorB": 0,
          "textColorG": 104,
          "textColorR": 49
        }
      },
      {
        "classname": "Button",
        "name": null,
        "children": [],
        "options": {
          "__type": "ButtonSurrogate:#EditorCommon.JsonModel.Component.GUI",
          "classname": "Button",
          "name": "Button_12",
          "ZOrder": 0,
          "actiontag": 13767006,
          "anchorPointX": 0.5,
          "anchorPointY": 0.5,
          "classType": "CocoStudio.EngineAdapterWrap.CSButton",
          "colorB": 255,
          "colorG": 255,
          "colorR": 255,
          "customProperty": "",
          "flipX": false,
          "flipY": false,
          "height": 44,
          "ignoreSize": true,
          "layoutParameter": null,
          "opacity": 255,
          "positionPercentX": 0.79375,
          "positionPercentY": 0.115625,
          "positionType": 0,
          "rotation": 0,
          "scaleX": 1,
          "scaleY": 1,
          "sizePercentX": 0.14791666,
          "sizePercentY": 0.06875,
          "sizeType": 0,
          "tag": 115,
          "touchAble": true,
          "useMergedTexture": false,
          "visible": true,
          "width": 142,
          "x": 762,
          "y": 74,
          "capInsetsHeight": 1,
          "capInsetsWidth": 1,
          "capInsetsX": 0,
          "capInsetsY": 0,
          "disabled": null,
          "disabledData": {
            "path": null,
            "plistFile": null,
            "resourceType": 0
          },
          "fontName": "微软雅黑",
          "fontSize": 28,
          "fontType": 0,
          "normal": null,
          "normalData": {
            "path": "anniversary_button.png",
            "plistFile": "",
            "resourceType": 0
          },
          "pressed": null,
          "pressedData": {
            "path": null,
            "plistFile": null,
            "resourceType": 0
          },
          "scale9Enable": false,
          "scale9Height": 44,
          "scale9Width": 142,
          "text": "兑换",
          "textColorB": 0,
          "textColorG": 104,
          "textColorR": 49
        }
      },
      {
        "classname": "Label",
        "name": null,
        "children": [],
        "options": {
          "__type": "LabelSurrogate:#EditorCommon.JsonModel.Component.GUI",
          "classname": "Label",
          "name": "Label_13",
          "ZOrder": 0,
          "actiontag": 24155878,
          "anchorPointX": 0.5,
          "anchorPointY": 0.5,
          "classType": "CocoStudio.EngineAdapterWrap.CSLabel",
          "colorB": 4,
          "colorG": 83,
          "colorR": 213,
          "customProperty": "",
          "flipX": false,
          "flipY": false,
          "height": 40,
          "ignoreSize": false,
          "layoutParameter": null,
          "opacity": 255,
          "positionPercentX": 0.529166639,
          "positionPercentY": 0.65625,
          "positionType": 0,
          "rotation": 0,
          "scaleX": 1,
          "scaleY": 1,
          "sizePercentX": 0.445833325,
          "sizePercentY": 0.0625,
          "sizeType": 0,
          "tag": 116,
          "touchAble": false,
          "useMergedTexture": false,
          "visible": true,
          "width": 428,
          "x": 508,
          "y": 420,
          "areaHeight": 40,
          "areaWidth": 428,
          "fontFile": null,
          "fontName": "微软雅黑",
          "fontSize": 14,
          "hAlignment": 0,
          "text": "",
          "touchScaleEnable": false,
          "vAlignment": 1
        }
      },
      {
        "classname": "Label",
        "name": null,
        "children": [],
        "options": {
          "__type": "LabelSurrogate:#EditorCommon.JsonModel.Component.GUI",
          "classname": "Label",
          "name": "Label_14",
          "ZOrder": 0,
          "actiontag": 18761711,
          "anchorPointX": 0.5,
          "anchorPointY": 0.5,
          "classType": "CocoStudio.EngineAdapterWrap.CSLabel",
          "colorB": 186,
          "colorG": 247,
          "colorR": 253,
          "customProperty": "",
          "flipX": false,
          "flipY": false,
          "height": 84,
          "ignoreSize": false,
          "layoutParameter": null,
          "opacity": 255,
          "positionPercentX": 0.6041667,
          "positionPercentY": 0.7625,
          "positionType": 0,
          "rotation": 0,
          "scaleX": 1,
          "scaleY": 1,
          "sizePercentX": 0.577083349,
          "sizePercentY": 0.13125,
          "sizeType": 0,
          "tag": 117,
          "touchAble": false,
          "useMergedTexture": false,
          "visible": true,
          "width": 554,
          "x": 580,
          "y": 488,
          "areaHeight": 84,
          "areaWidth": 554,
          "fontFile": null,
          "fontName": "微软雅黑",
          "fontSize": 15,
          "hAlignment": 0,
          "text": "",
          "touchScaleEnable": false,
          "vAlignment": 0
        }
      },
      {
        "classname": "Label",
        "name": null,
        "children": [],
        "options": {
          "__type": "LabelSurrogate:#EditorCommon.JsonModel.Component.GUI",
          "classname": "Label",
          "name": "Label_16",
          "ZOrder": 0,
          "actiontag": 9266787,
          "anchorPointX": 0.5,
          "anchorPointY": 0.5,
          "classType": "CocoStudio.EngineAdapterWrap.CSLabel",
          "colorB": 0,
          "colorG": 247,
          "colorR": 255,
          "customProperty": "",
          "flipX": false,
          "flipY": false,
          "height": 0,
          "ignoreSize": true,
          "layoutParameter": null,
          "opacity": 255,
          "positionPercentX": 0.213541672,
          "positionPercentY": 0.503125,
          "positionType": 0,
          "rotation": 0,
          "scaleX": 1,
          "scaleY": 1,
          "sizePercentX": 0.114583336,
          "sizePercentY": 0.03125,
          "sizeType": 0,
          "tag": 119,
          "touchAble": false,
          "useMergedTexture": false,
          "visible": true,
          "width": 0,
          "x": 205,
          "y": 322,
          "areaHeight": 0,
          "areaWidth": 0,
          "fontFile": null,
          "fontName": "微软雅黑",
          "fontSize": 14,
          "hAlignment": 0,
          "text": "",
          "touchScaleEnable": false,
          "vAlignment": 0
        }
      },
      {
        "classname": "Label",
        "name": null,
        "children": [],
        "options": {
          "__type": "LabelSurrogate:#EditorCommon.JsonModel.Component.GUI",
          "classname": "Label",
          "name": "Label_17",
          "ZOrder": 0,
          "actiontag": 61929123,
          "anchorPointX": 0.5,
          "anchorPointY": 0.5,
          "classType": "CocoStudio.EngineAdapterWrap.CSLabel",
          "colorB": 255,
          "colorG": 255,
          "colorR": 255,
          "customProperty": "",
          "flipX": false,
          "flipY": false,
          "height": 21,
          "ignoreSize": true,
          "layoutParameter": null,
          "opacity": 255,
          "positionPercentX": 0.410416663,
          "positionPercentY": 0.503125,
          "positionType": 0,
          "rotation": 0,
          "scaleX": 1,
          "scaleY": 1,
          "sizePercentX": 0.121875,
          "sizePercentY": 0.0328125,
          "sizeType": 0,
          "tag": 120,
          "touchAble": false,
          "useMergedTexture": false,
          "visible": true,
          "width": 117,
          "x": 394,
          "y": 322,
          "areaHeight": 0,
          "areaWidth": 0,
          "fontFile": null,
          "fontName": "微软雅黑",
          "fontSize": 16,
          "hAlignment": 1,
          "text": " เหรียญที่ระลึก",
          "touchScaleEnable": false,
          "vAlignment": 1
        }
      },
      {
        "classname": "Label",
        "name": null,
        "children": [],
        "options": {
          "__type": "LabelSurrogate:#EditorCommon.JsonModel.Component.GUI",
          "classname": "Label",
          "name": "Label_18",
          "ZOrder": 0,
          "actiontag": 12112847,
          "anchorPointX": 0.5,
          "anchorPointY": 0.5,
          "classType": "CocoStudio.EngineAdapterWrap.CSLabel",
          "colorB": 1,
          "colorG": 59,
          "colorR": 120,
          "customProperty": "",
          "flipX": false,
          "flipY": false,
          "height": 21,
          "ignoreSize": true,
          "layoutParameter": null,
          "opacity": 255,
          "positionPercentX": 0.410416663,
          "positionPercentY": 0.4453125,
          "positionType": 0,
          "rotation": 0,
          "scaleX": 1,
          "scaleY": 1,
          "sizePercentX": 0.128125,
          "sizePercentY": 0.0328125,
          "sizeType": 0,
          "tag": 121,
          "touchAble": false,
          "useMergedTexture": false,
          "visible": true,
          "width": 123,
          "x": 394,
          "y": 285,
          "areaHeight": 0,
          "areaWidth": 0,
          "fontFile": null,
          "fontName": "微软雅黑",
          "fontSize": 16,
          "hAlignment": 1,
          "text": "เหรียญครบรอบ 1 ป",
          "touchScaleEnable": false,
          "vAlignment": 1
        }
      },
      {
        "classname": "Label",
        "name": null,
        "children": [],
        "options": {
          "__type": "LabelSurrogate:#EditorCommon.JsonModel.Component.GUI",
          "classname": "Label",
          "name": "Label_18_0",
          "ZOrder": 0,
          "actiontag": 29450093,
          "anchorPointX": 0.5,
          "anchorPointY": 0.5,
          "classType": "CocoStudio.EngineAdapterWrap.CSLabel",
          "colorB": 1,
          "colorG": 59,
          "colorR": 120,
          "customProperty": "",
          "flipX": false,
          "flipY": false,
          "height": 21,
          "ignoreSize": true,
          "layoutParameter": null,
          "opacity": 255,
          "positionPercentX": 0.410416663,
          "positionPercentY": 0.4125,
          "positionType": 0,
          "rotation": 0,
          "scaleX": 1,
          "scaleY": 1,
          "sizePercentX": 0.04375,
          "sizePercentY": 0.0328125,
          "sizeType": 0,
          "tag": 123,
          "touchAble": false,
          "useMergedTexture": false,
          "visible": true,
          "width": 42,
          "x": 394,
          "y": 264,
          "areaHeight": 0,
          "areaWidth": 0,
          "fontFile": null,
          "fontName": "微软雅黑",
          "fontSize": 16,
          "hAlignment": 1,
          "text": "(ถาวร)",
          "touchScaleEnable": false,
          "vAlignment": 1
        }
      },
      {
        "classname": "Label",
        "name": null,
        "children": [],
        "options": {
          "__type": "LabelSurrogate:#EditorCommon.JsonModel.Component.GUI",
          "classname": "Label",
          "name": "Label_21",
          "ZOrder": 0,
          "actiontag": 47800977,
          "anchorPointX": 0.5,
          "anchorPointY": 0.5,
          "classType": "CocoStudio.EngineAdapterWrap.CSLabel",
          "colorB": 255,
          "colorG": 255,
          "colorR": 255,
          "customProperty": "",
          "flipX": false,
          "flipY": false,
          "height": 0,
          "ignoreSize": true,
          "layoutParameter": null,
          "opacity": 255,
          "positionPercentX": 0.702083349,
          "positionPercentY": 0.503125,
          "positionType": 0,
          "rotation": 0,
          "scaleX": 1,
          "scaleY": 1,
          "sizePercentX": 0.270833343,
          "sizePercentY": 0.0328125,
          "sizeType": 0,
          "tag": 124,
          "touchAble": false,
          "useMergedTexture": false,
          "visible": true,
          "width": 0,
          "x": 674,
          "y": 322,
          "areaHeight": 0,
          "areaWidth": 0,
          "fontFile": null,
          "fontName": "微软雅黑",
          "fontSize": 16,
          "hAlignment": 0,
          "text": "",
          "touchScaleEnable": false,
          "vAlignment": 0
        }
      },
      {
        "classname": "Label",
        "name": null,
        "children": [],
        "options": {
          "__type": "LabelSurrogate:#EditorCommon.JsonModel.Component.GUI",
          "classname": "Label",
          "name": "Label_23",
          "ZOrder": 0,
          "actiontag": 17745440,
          "anchorPointX": 0.5,
          "anchorPointY": 0.5,
          "classType": "CocoStudio.EngineAdapterWrap.CSLabel",
          "colorB": 1,
          "colorG": 59,
          "colorR": 120,
          "customProperty": "",
          "flipX": false,
          "flipY": false,
          "height": 21,
          "ignoreSize": true,
          "layoutParameter": null,
          "opacity": 255,
          "positionPercentX": 0.60625,
          "positionPercentY": 0.4390625,
          "positionType": 0,
          "rotation": 0,
          "scaleX": 1,
          "scaleY": 1,
          "sizePercentX": 0.09375,
          "sizePercentY": 0.0328125,
          "sizeType": 0,
          "tag": 126,
          "touchAble": false,
          "useMergedTexture": false,
          "visible": true,
          "width": 90,
          "x": 582,
          "y": 281,
          "areaHeight": 0,
          "areaWidth": 0,
          "fontFile": null,
          "fontName": "微软雅黑",
          "fontSize": 16,
          "hAlignment": 0,
          "text": "ค่า EXP 200",
          "touchScaleEnable": false,
          "vAlignment": 0
        }
      },
      {
        "classname": "Label",
        "name": null,
        "children": [],
        "options": {
          "__type": "LabelSurrogate:#EditorCommon.JsonModel.Component.GUI",
          "classname": "Label",
          "name": "Label_24",
          "ZOrder": 0,
          "actiontag": 53933198,
          "anchorPointX": 0.5,
          "anchorPointY": 0.5,
          "classType": "CocoStudio.EngineAdapterWrap.CSLabel",
          "colorB": 1,
          "colorG": 59,
          "colorR": 120,
          "customProperty": "",
          "flipX": false,
          "flipY": false,
          "height": 21,
          "ignoreSize": true,
          "layoutParameter": null,
          "opacity": 255,
          "positionPercentX": 0.79375,
          "positionPercentY": 0.4390625,
          "positionType": 0,
          "rotation": 0,
          "scaleX": 1,
          "scaleY": 1,
          "sizePercentX": 0.1125,
          "sizePercentY": 0.0328125,
          "sizeType": 0,
          "tag": 127,
          "touchAble": false,
          "useMergedTexture": false,
          "visible": true,
          "width": 108,
          "x": 762,
          "y": 281,
          "areaHeight": 0,
          "areaWidth": 0,
          "fontFile": null,
          "fontName": "微软雅黑",
          "fontSize": 16,
          "hAlignment": 0,
          "text": "ไอเทม 20 ครั้ง",
          "touchScaleEnable": false,
          "vAlignment": 0
        }
      },
      {
        "classname": "Button",
        "name": null,
        "children": [],
        "options": {
          "__type": "ButtonSurrogate:#EditorCommon.JsonModel.Component.GUI",
          "classname": "Button",
          "name": "Button_25",
          "ZOrder": 0,
          "actiontag": 46318842,
          "anchorPointX": 0.5,
          "anchorPointY": 0.5,
          "classType": "CocoStudio.EngineAdapterWrap.CSButton",
          "colorB": 255,
          "colorG": 255,
          "colorR": 255,
          "customProperty": "",
          "flipX": false,
          "flipY": false,
          "height": 69,
          "ignoreSize": true,
          "layoutParameter": null,
          "opacity": 255,
          "positionPercentX": 0.9145833,
          "positionPercentY": 0.85,
          "positionType": 0,
          "rotation": 0,
          "scaleX": 1,
          "scaleY": 1,
          "sizePercentX": 0.0729166642,
          "sizePercentY": 0.1078125,
          "sizeType": 0,
          "tag": 128,
          "touchAble": true,
          "useMergedTexture": false,
          "visible": true,
          "width": 70,
          "x": 878,
          "y": 544,
          "capInsetsHeight": 1,
          "capInsetsWidth": 1,
          "capInsetsX": 0,
          "capInsetsY": 0,
          "disabled": null,
          "disabledData": {
            "path": null,
            "plistFile": null,
            "resourceType": 0
          },
          "fontName": "微软雅黑",
          "fontSize": 14,
          "fontType": 0,
          "normal": null,
          "normalData": {
            "path": "anniversary_close.png",
            "plistFile": "",
            "resourceType": 0
          },
          "pressed": null,
          "pressedData": {
            "path": null,
            "plistFile": null,
            "resourceType": 0
          },
          "scale9Enable": false,
          "scale9Height": 69,
          "scale9Width": 70,
          "text": "",
          "textColorB": 255,
          "textColorG": 255,
          "textColorR": 255
        }
      }
    ],
    "options": {
      "__type": "PanelSurrogate:#EditorCommon.JsonModel.Component.GUI",
      "classname": "Panel",
      "name": "Panel_14",
      "ZOrder": 0,
      "actiontag": -1,
      "anchorPointX": 0,
      "anchorPointY": 0,
      "classType": "CocoStudio.EngineAdapterWrap.CSPanel",
      "colorB": 255,
      "colorG": 255,
      "colorR": 255,
      "customProperty": "",
      "flipX": false,
      "flipY": false,
      "height": 640,
      "ignoreSize": false,
      "layoutParameter": null,
      "opacity": 255,
      "positionPercentX": 0,
      "positionPercentY": 0,
      "positionType": 0,
      "rotation": 0,
      "scaleX": 1,
      "scaleY": 1,
      "sizePercentX": 1,
      "sizePercentY": 1,
      "sizeType": 0,
      "tag": 3,
      "touchAble": true,
      "useMergedTexture": false,
      "visible": true,
      "width": 960,
      "x": 0,
      "y": 0,
      "adaptScreen": false,
      "backGroundImage": null,
      "backGroundImageData": null,
      "backGroundScale9Enable": false,
      "bgColorB": 255,
      "bgColorG": 200,
      "bgColorOpacity": 0,
      "bgColorR": 150,
      "bgEndColorB": 255,
      "bgEndColorG": 200,
      "bgEndColorR": 150,
      "bgStartColorB": 255,
      "bgStartColorG": 255,
      "bgStartColorR": 255,
      "capInsetsHeight": 1,
      "capInsetsWidth": 1,
      "capInsetsX": 0,
      "capInsetsY": 0,
      "clipAble": false,
      "colorType": 1,
      "layoutType": 0,
      "vectorX": 0,
      "vectorY": -0.5
    }
  }
}